mathmatrix/__init__.py
mathmatrix/config.py
mathmatrix/matrix.py
mathmatrix-0.5.dist-info/LICENSE
mathmatrix-0.5.dist-info/METADATA
mathmatrix-0.5.dist-info/WHEEL
mathmatrix-0.5.dist-info/top_level.txt
mathmatrix-0.5.dist-info/RECORD
