Metadata-Version: 2.1
Name: mathmatrix
Version: 0.5
Summary: A package for Python that lets you create and perform various operations on Matrices sucjh as finding the adjoint, inverse, determinant of a matrix, etc..
Home-page: https://github.com/Nectres/mathmatrix.git
Author: Keerthi Vasan S A
Author-email: sakeerthi23@gmail.com
License: MIT
Download-URL: https://github.com/Nectres/mathmatrix/archive/refs/tags/Alpha.tar.gz
Keywords: matrix,math,mathmatrix,matrices,matrix inverse,determinant
Platform: UNKNOWN
Classifier: Development Status :: 3 - Alpha
Classifier: Topic :: Scientific/Engineering :: Mathematics
Classifier: License :: OSI Approved :: MIT License
Classifier: Programming Language :: Python :: 3
